pickle_secure/__init__.py
pickle_secure/pickle_secure.py
pickle_secure/py.typed
pickle_secure/utils.py
pickle_secure-0.99.9.dist-info/LICENSE.txt
pickle_secure-0.99.9.dist-info/METADATA
pickle_secure-0.99.9.dist-info/WHEEL
pickle_secure-0.99.9.dist-info/RECORD
