Metadata-Version: 2.1
Name: pickle-secure
Version: 0.99.9
Summary: Easily create encrypted pickle files
Home-page: https://github.com/spapanik/pickle-secure
License: LGPL-3.0+
Keywords: pickle,AES,secure storage
Author: Stephanos Kuma
Author-email: stephanos@kuma.ai
Requires-Python: >=3.8,<4.0
Classifier: Development Status :: 4 - Beta
Classifier: License :: OSI Approved :: GNU Lesser General Public License v3 or later (LGPLv3+)
Classifier: Operating System :: OS Independent
Classifier: Programming Language :: Python :: 3
Classifier: Programming Language :: Python :: 3.8
Classifier: Programming Language :: Python :: 3.9
Classifier: Programming Language :: Python :: 3.10
Classifier: Programming Language :: Python :: 3.11
Requires-Dist: cryptography (>=39.0.1)
Project-URL: Repository, https://github.com/spapanik/pickle-secure
